{
  "$schema": "http://json-schema.org/schema#",
  "$id": "http://jorodox.org/schemas/country_factor.json",
  "type": "object",
  "definitions": {
    "country_factor": {
      "type": "object",
      "properties": {
        "factor": {
          "type": "number"
        },
        "modifier": {
          "$makeArray": {
            "type": "array",
            "items": {
              "$ref": "country_factor.json#/definitions/country_factor"
            }
          }
        }
      }
    }
  }
}